tests/__init__.py
tests/test.py
tests/test_local.py
video2srt/__init__.py
video2srt/livecaptions2srt.py
video2srt/main.py
video2srt/test_video.mp4
video2srt/video2srt.py
video2srt-0.2.6.dist-info/licenses/LICENSE
video2srt-0.2.6.dist-info/METADATA
video2srt-0.2.6.dist-info/WHEEL
video2srt-0.2.6.dist-info/top_level.txt
video2srt-0.2.6.dist-info/RECORD
