Metadata-Version: 2.4
Name: video2srt
Version: 0.2.6
Summary: This is a simple project that converts speech from video into subtitles by brice
Home-page: https://github.com/Brice2012/video2srt_python.git
Author: YeJunjie (nickname: Brice)
Author-email: ye@okwords.cn
Requires-Python: >=3.13.5
License-File: LICENSE
Requires-Dist: requests>=2.32.3
Requires-Dist: urllib3>=2.3.0
Requires-Dist: numpy>=2.1.3
Requires-Dist: pandas>=2.2.3
Requires-Dist: openai-whisper>=20250625
Requires-Dist: torch>=2.9.1
Requires-Dist: sentencepiece>=0.2.1
Requires-Dist: deep-translator>=1.11.4
Requires-Dist: transformers>=4.57.3
Dynamic: license-file
